testcontainers/keycloak/__init__.py
tests/test_keycloak.py
testcontainers_keycloak-0.0.1rc1.dist-info/METADATA
testcontainers_keycloak-0.0.1rc1.dist-info/WHEEL
testcontainers_keycloak-0.0.1rc1.dist-info/top_level.txt
testcontainers_keycloak-0.0.1rc1.dist-info/RECORD
